boeah/__init__.py
boeah/application.py
boeah/commands/__init__.py
boeah/commands/command.py
boeah/commands/routes.py
boeah/commands/server.py
boeah/console.py
boeah/controller.py
boeah/db/__init__.py
boeah/db/db.py
boeah/db/drivers/__init__.py
boeah/db/drivers/postgre.py
boeah/db/model/__init__.py
boeah/db/model/model.py
boeah/http/__init__.py
boeah/http/kernel.py
boeah/http/request.py
boeah/http/response.py
boeah/request.py
boeah/router.py
boeah-0.1.4.dist-info/WHEEL
boeah-0.1.4.dist-info/METADATA
boeah-0.1.4.dist-info/RECORD
