Metadata-Version: 2.1
Name: boeah
Version: 0.1.4
Summary: Boeah Framework
License: MIT
Author: Fathur
Author-email: hi.fathur.rohman@gmail.com
Requires-Python: >=3.7,<4.0
Classifier: License :: OSI Approved :: MIT License
Classifier: Programming Language :: Python :: 3
Classifier: Programming Language :: Python :: 3.10
Classifier: Programming Language :: Python :: 3.7
Classifier: Programming Language :: Python :: 3.8
Classifier: Programming Language :: Python :: 3.9
Requires-Dist: Werkzeug (>=2.0.3,<3.0.0)
Requires-Dist: ipython (>=7.32,<8.0)
Requires-Dist: python-dotenv (>=0.19.2,<0.20.0)
Requires-Dist: rich (>=11.2.0,<12.0.0)
